congress_dashboard/__init__.py
congress_dashboard/version.py
congress_dashboard/api/__init__.py
congress_dashboard/api/congress.py
congress_dashboard/datasources/__init__.py
congress_dashboard/datasources/forms.py
congress_dashboard/datasources/panel.py
congress_dashboard/datasources/tables.py
congress_dashboard/datasources/urls.py
congress_dashboard/datasources/utils.py
congress_dashboard/datasources/views.py
congress_dashboard/datasources/templates/datasources/_create.html
congress_dashboard/datasources/templates/datasources/_datasource_overview.html
congress_dashboard/datasources/templates/datasources/_detail_overview.html
congress_dashboard/datasources/templates/datasources/create.html
congress_dashboard/datasources/templates/datasources/datasource_detail.html
congress_dashboard/datasources/templates/datasources/detail.html
congress_dashboard/datasources/templates/datasources/index.html
congress_dashboard/enabled/_50_policy.py
congress_dashboard/enabled/_60_policies.py
congress_dashboard/enabled/_70_datasources.py
congress_dashboard/enabled/_75_monitoring.py
congress_dashboard/enabled/_80_library.py
congress_dashboard/enabled/__init__.py
congress_dashboard/library/__init__.py
congress_dashboard/library/panel.py
congress_dashboard/library/tables.py
congress_dashboard/library/urls.py
congress_dashboard/library/views.py
congress_dashboard/library/templates/library/_detail_overview.html
congress_dashboard/library/templates/library/detail.html
congress_dashboard/library/templates/library/index.html
congress_dashboard/monitoring/__init__.py
congress_dashboard/monitoring/panel.py
congress_dashboard/monitoring/tables.py
congress_dashboard/monitoring/urls.py
congress_dashboard/monitoring/views.py
congress_dashboard/monitoring/templates/monitoring/index.html
congress_dashboard/policies/__init__.py
congress_dashboard/policies/forms.py
congress_dashboard/policies/panel.py
congress_dashboard/policies/tables.py
congress_dashboard/policies/urls.py
congress_dashboard-6.0.0.dist-info/AUTHORS
congress_dashboard-6.0.0.dist-info/LICENSE
congress_dashboard-6.0.0.dist-info/METADATA
congress_dashboard-6.0.0.dist-info/WHEEL
congress_dashboard-6.0.0.dist-info/pbr.json
congress_dashboard-6.0.0.dist-info/top_level.txt
congress_dashboard-6.0.0.dist-info/RECORD
