Metadata-Version: 2.1
Name: congress-dashboard
Version: 6.0.0
Summary: Horizon Plugin for Congress
Home-page: https://github.com/openstack/congress-dashboard
Author: OpenStack
Author-email: openstack-discuss@lists.openstack.org
License: UNKNOWN
Platform: UNKNOWN
Classifier: Environment :: OpenStack
Classifier: Intended Audience :: Information Technology
Classifier: Intended Audience :: System Administrators
Classifier: License :: OSI Approved :: Apache Software License
Classifier: Operating System :: POSIX :: Linux
Classifier: Programming Language :: Python
Classifier: Programming Language :: Python :: 3
Classifier: Programming Language :: Python :: 3.6
Classifier: Programming Language :: Python :: 3.7
Requires-Dist: pbr (!=2.1.0,>=2.0.0)
Requires-Dist: django-compressor (>=2.0)
Requires-Dist: keystoneauth1 (>=3.4.0)
Requires-Dist: python-congressclient (<2000,>=1.9.0)
Requires-Dist: horizon (>=17.1.0)
